edureporter/__init__.py
edureporter/reporter.py
edureporter/storage.py
edureporter/utils.py
edureporter/fonts/__init__.py
testapp/__init__.py
testapp/manage.py
testapp/settings.py
testapp/urls.py
testapp/wsgi.py
testapp/app/__init__.py
testapp/app/reports/__init__.py
testapp/app/reports/simple_report/__init__.py
testapp/app/reports/simple_report/report.py
testapp/app/tests/__init__.py
testapp/app/tests/test_report.py
testapp/app/tests/test_storages.py
edureporter-2.1.0.dist-info/LICENSE
edureporter-2.1.0.dist-info/METADATA
edureporter-2.1.0.dist-info/WHEEL
edureporter-2.1.0.dist-info/top_level.txt
edureporter-2.1.0.dist-info/RECORD
