Metadata-Version: 2.1
Name: edureporter
Version: 2.1.0
Summary: Пакет инструментов для построения отчетных систем
Author-email: "АО \"БАРС Груп\"" <education_dev@bars-open.ru>
Classifier: Intended Audience :: Developers
Classifier: Environment :: Web Environment
Classifier: Natural Language :: Russian
Classifier: Operating System :: OS Independent
Classifier: Development Status :: 5 - Production/Stable
Classifier: Programming Language :: Python :: 3.9
Classifier: Programming Language :: Python :: 3.10
Classifier: Programming Language :: Python :: 3.11
Classifier: Programming Language :: Python :: 3.12
Classifier: Framework :: Django :: 3.2
Classifier: Framework :: Django :: 4.0
Classifier: Framework :: Django :: 4.1
Classifier: Framework :: Django :: 4.2
Classifier: Framework :: Django :: 5.0
Requires-Python: >=3.9
License-File: LICENSE
Requires-Dist: Django
Requires-Dist: m3-simple-report==1.6.0
Requires-Dist: Pillow==10.2.0
